odoo/addons/delivery_purchase/README.rst
odoo/addons/delivery_purchase/__init__.py
odoo/addons/delivery_purchase/__manifest__.py
odoo/addons/delivery_purchase/i18n/delivery_purchase.pot
odoo/addons/delivery_purchase/i18n/es.po
odoo/addons/delivery_purchase/i18n/it.po
odoo/addons/delivery_purchase/models/__init__.py
odoo/addons/delivery_purchase/models/delivery_carrier.py
odoo/addons/delivery_purchase/models/purchase_order.py
odoo/addons/delivery_purchase/models/stock_picking.py
odoo/addons/delivery_purchase/readme/CONTRIBUTORS.md
odoo/addons/delivery_purchase/readme/DESCRIPTION.md
odoo/addons/delivery_purchase/readme/USAGE.md
odoo/addons/delivery_purchase/static/description/icon.png
odoo/addons/delivery_purchase/static/description/index.html
odoo/addons/delivery_purchase/tests/__init__.py
odoo/addons/delivery_purchase/tests/test_delivery_purchase.py
odoo/addons/delivery_purchase/views/purchase_order_view.xml
odoo/addons/delivery_purchase/views/stock_picking_view.xml
odoo_addon_delivery_purchase-18.0.1.0.0.2.dist-info/METADATA
odoo_addon_delivery_purchase-18.0.1.0.0.2.dist-info/WHEEL
odoo_addon_delivery_purchase-18.0.1.0.0.2.dist-info/top_level.txt
odoo_addon_delivery_purchase-18.0.1.0.0.2.dist-info/RECORD
